rampedpyrox/__init__.py
rampedpyrox/core_functions.py
rampedpyrox/exceptions.py
rampedpyrox/model.py
rampedpyrox/model_helper.py
rampedpyrox/plotting_helper.py
rampedpyrox/ratedata.py
rampedpyrox/results.py
rampedpyrox/results_helper.py
rampedpyrox/summary_helper.py
rampedpyrox/timedata.py
rampedpyrox/timedata_helper.py
rampedpyrox-1.0.4.dist-info/METADATA
rampedpyrox-1.0.4.dist-info/WHEEL
rampedpyrox-1.0.4.dist-info/top_level.txt
rampedpyrox-1.0.4.dist-info/RECORD
