Metadata-Version: 2.1
Name: rampedpyrox
Version: 1.0.4
Summary: Ramped PyrOx kinetic and isotope analysis
Home-page: https://github.com/FluvialSeds/rampedpyrox
Download-URL: https://github.com/FluvialSeds/rampedpyrox/tarball/1.0.4
Author: Jordon D. Hemingway
Author-email: jordon.hemingway@erdw.ethz.ch
License: GNU GPL Version 3
Keywords: geochemistry,isotopes,kinetics,inverse modeling,carbon cycle
Classifier: Development Status :: 3 - Alpha
Classifier: Intended Audience :: Science/Research
Classifier: License :: Free for non-commercial use
Classifier: Programming Language :: Python
Classifier: Programming Language :: Python :: 3
Classifier: Programming Language :: Python :: 2
Classifier: Programming Language :: Python :: 3.5
Classifier: Programming Language :: Python :: 2.7
Classifier: Topic :: Scientific/Engineering
Requires-Dist: matplotlib
Requires-Dist: numpy
Requires-Dist: pandas
Requires-Dist: scipy
